carbon/__init__.py
carbon/__main__.py
carbon/carbon.py
carbon/cli.py
pybites_carbon-0.8.1.dist-info/licenses/LICENSE
pybites_carbon-0.8.1.dist-info/METADATA
pybites_carbon-0.8.1.dist-info/WHEEL
pybites_carbon-0.8.1.dist-info/entry_points.txt
pybites_carbon-0.8.1.dist-info/top_level.txt
pybites_carbon-0.8.1.dist-info/RECORD
