Metadata-Version: 2.4
Name: pybites-carbon
Version: 0.8.1
Summary: Create code images from CLI using carbon
Author-email: Pybites <info@pybit.es>
License: MIT License
Project-URL: Source, https://github.com/PyBites-Open-Source/pybites-carbon
Requires-Python: >=3.10
License-File: LICENSE
Requires-Dist: playwright>=1.47.0
Requires-Dist: pyperclip>=1.9.0
Requires-Dist: python-dotenv>=1.0.1
Dynamic: license-file
